MANIFEST.in
README.rst
setup.py
docs/HISTORY.txt
docs/INSTALL.txt
docs/LICENSE.GPL
docs/LICENSE.txt
docs/TODO.txt
unice/.DS_Store
unice/__init__.py
unice.portlet.imagelegendee.egg-info/PKG-INFO
unice.portlet.imagelegendee.egg-info/SOURCES.txt
unice.portlet.imagelegendee.egg-info/dependency_links.txt
unice.portlet.imagelegendee.egg-info/entry_points.txt
unice.portlet.imagelegendee.egg-info/namespace_packages.txt
unice.portlet.imagelegendee.egg-info/not-zip-safe
unice.portlet.imagelegendee.egg-info/requires.txt
unice.portlet.imagelegendee.egg-info/top_level.txt
unice/portlet/.DS_Store
unice/portlet/__init__.py
unice/portlet/imagelegendee/__init__.py
unice/portlet/imagelegendee/configure.zcml
unice/portlet/imagelegendee/imagelegendeeportlet.pt
unice/portlet/imagelegendee/imagelegendeeportlet.py
unice/portlet/imagelegendee/vocabularies.py
unice/portlet/imagelegendee/browser/.DS_Store
unice/portlet/imagelegendee/browser/__init__.py
unice/portlet/imagelegendee/browser/configure.zcml
unice/portlet/imagelegendee/browser/stylesheets/styles.css
unice/portlet/imagelegendee/profiles/.DS_Store
unice/portlet/imagelegendee/profiles/default/cssregistry.xml
unice/portlet/imagelegendee/profiles/default/metadata.xml
unice/portlet/imagelegendee/profiles/default/portlets.xml
unice/portlet/imagelegendee/tests/__init__.py
unice/portlet/imagelegendee/tests/base.py
unice/portlet/imagelegendee/tests/test_portlet.py